petfetchpy/__init__.py
petfetchpy/__main__.py
petfetchpy/cli.py
petfetchpy/colors.py
petfetchpy/ascii-pets/.git
petfetchpy/ascii-pets/BIRD.ascii
petfetchpy/ascii-pets/SHARK.ascii
petfetchpy/ascii-pets/bird.ascii
petfetchpy/ascii-pets/cat.ascii
petfetchpy/ascii-pets/dog.ascii
petfetchpy/ascii-pets/frog.ascii
petfetchpy/ascii-pets/mouse.ascii
petfetchpy/ascii-pets/shark.ascii
petfetchpy-1.0.0.dist-info/METADATA
petfetchpy-1.0.0.dist-info/WHEEL
petfetchpy-1.0.0.dist-info/entry_points.txt
petfetchpy-1.0.0.dist-info/licenses/LICENSE
petfetchpy-1.0.0.dist-info/RECORD
