Metadata-Version: 2.4
Name: petfetchpy
Version: 1.0.0
Summary: A cute pet fetch utility
Project-URL: Homepage, https://github.com/KittKat7/petfetchpy
Project-URL: Issues, https://github.com/KittKat7/petfetchpy/issues
Author-email: KittKat <kittkat@kittkat.xyz>
License-Expression: GPL-3.0-or-later
License-File: LICENSE
Classifier: Operating System :: OS Independent
Classifier: Programming Language :: Python :: 3
Requires-Python: >=3.8
Requires-Dist: distro>=1.9.0
Requires-Dist: py-cpuinfo>=9.0.0
